{
    "module": "pygsti.models.explicitmodel",
    "class": "ExplicitOpModel",
    "version": 0,
    "state_space": {
        "module": "pygsti.baseobjs.statespace",
        "class": "QubitSpace",
        "version": 0,
        "qudit_labels": [
            0
        ],
        "qudit_udims": [
            2
        ],
        "qubit_labels": [
            0
        ]
    },
    "basis": {
        "module": "pygsti.baseobjs.basis",
        "class": "BuiltinBasis",
        "version": 0,
        "name": "pp",
        "sparse": false,
        "state_space": {
            "module": "pygsti.baseobjs.statespace",
            "class": "QubitSpace",
            "version": 0,
            "qudit_labels": [
                0
            ],
            "qudit_udims": [
                2
            ],
            "qubit_labels": [
                0
            ]
        }
    },
    "default_gate_type": "static",
    "default_prep_type": [
        "static"
    ],
    "default_povm_type": [
        "static"
    ],
    "default_instrument_type": [
        "static"
    ],
    "prep_prefix": "rho",
    "effect_prefix": "E",
    "gate_prefix": "G",
    "povm_prefix": "M",
    "instrument_prefix": "I",
    "evotype": "densitymx",
    "simulator": {
        "module": "pygsti.forwardsims.matrixforwardsim",
        "class": "MatrixForwardSimulator",
        "version": 0,
        "mode": "time_independent"
    },
    "default_gauge_group": {
        "module": "pygsti.models.gaugegroup",
        "class": "TPGaugeGroup",
        "version": 0,
        "state_space_dimension": 4,
        "evotype": "densitymx",
        "basis": {
            "module": "pygsti.baseobjs.basis",
            "class": "BuiltinBasis",
            "version": 0,
            "name": "pp",
            "sparse": false,
            "state_space": {
                "module": "pygsti.baseobjs.statespace",
                "class": "QubitSpace",
                "version": 0,
                "qudit_labels": [
                    0
                ],
                "qudit_udims": [
                    2
                ],
                "qubit_labels": [
                    0
                ]
            }
        }
    },
    "parameter_interposer": null,
    "modelmembers": {
        "0": {
            "module": "pygsti.modelmembers.states.tpstate",
            "class": "TPState",
            "submembers": [],
            "state_space": {
                "module": "pygsti.baseobjs.statespace",
                "class": "QubitSpace",
                "version": 0,
                "qudit_labels": [
                    0
                ],
                "qudit_udims": [
                    2
                ],
                "qubit_labels": [
                    0
                ]
            },
            "evotype": "densitymx",
            "model_parameter_indices": [
                0,
                1,
                2
            ],
            "relative_submember_parameter_indices": [],
            "parameter_labels": [
                "VecElement 1",
                "VecElement 2",
                "VecElement 3"
            ],
            "parameter_bounds": null,
            "dense_superket_vector": [
                0.7071067811865476,
                -0.0006272219649114288,
                0.003034315538271469,
                0.7083078993811022
            ],
            "basis": {
                "module": "pygsti.baseobjs.basis",
                "class": "BuiltinBasis",
                "version": 0,
                "name": "pp",
                "sparse": false,
                "state_space": {
                    "module": "pygsti.baseobjs.statespace",
                    "class": "QubitSpace",
                    "version": 0,
                    "qudit_labels": [
                        0
                    ],
                    "qudit_udims": [
                        2
                    ],
                    "qubit_labels": [
                        0
                    ]
                }
            },
            "memberdict_types": [
                "preps"
            ],
            "memberdict_labels": [
                "rho0"
            ]
        },
        "1": {
            "module": "pygsti.modelmembers.states.fullstate",
            "class": "FullState",
            "submembers": [],
            "state_space": {
                "module": "pygsti.baseobjs.statespace",
                "class": "QubitSpace",
                "version": 0,
                "qudit_labels": [
                    0
                ],
                "qudit_udims": [
                    2
                ],
                "qubit_labels": [
                    0
                ]
            },
            "evotype": "densitymx",
            "model_parameter_indices": [
                3,
                4,
                5,
                6
            ],
            "relative_submember_parameter_indices": [],
            "parameter_labels": [
                "VecElement Re(0)",
                "VecElement Re(1)",
                "VecElement Re(2)",
                "VecElement Re(3)"
            ],
            "parameter_bounds": null,
            "dense_superket_vector": [
                0.7065358567758345,
                0.0008454277055588598,
                0.008052451039602159,
                0.706432192791826
            ],
            "basis": {
                "module": "pygsti.baseobjs.basis",
                "class": "BuiltinBasis",
                "version": 0,
                "name": "pp",
                "sparse": false,
                "state_space": {
                    "module": "pygsti.baseobjs.statespace",
                    "class": "QubitSpace",
                    "version": 0,
                    "qudit_labels": [
                        0
                    ],
                    "qudit_udims": [
                        2
                    ],
                    "qubit_labels": [
                        0
                    ]
                }
            }
        },
        "2": {
            "module": "pygsti.modelmembers.povms.fulleffect",
            "class": "FullPOVMEffect",
            "submembers": [
                1
            ],
            "state_space": {
                "module": "pygsti.baseobjs.statespace",
                "class": "QubitSpace",
                "version": 0,
                "qudit_labels": [
                    0
                ],
                "qudit_udims": [
                    2
                ],
                "qubit_labels": [
                    0
                ]
            },
            "evotype": "densitymx",
            "model_parameter_indices": [
                3,
                4,
                5,
                6
            ],
            "relative_submember_parameter_indices": [
                [
                    0,
                    1,
                    2,
                    3
                ]
            ],
            "parameter_labels": null,
            "parameter_bounds": null
        },
        "3": {
            "module": "pygsti.modelmembers.povms.complementeffect",
            "class": "ComplementPOVMEffect",
            "submembers": [
                2
            ],
            "state_space": {
                "module": "pygsti.baseobjs.statespace",
                "class": "QubitSpace",
                "version": 0,
                "qudit_labels": [
                    0
                ],
                "qudit_udims": [
                    2
                ],
                "qubit_labels": [
                    0
                ]
            },
            "evotype": "densitymx",
            "model_parameter_indices": [
                3,
                4,
                5,
                6
            ],
            "relative_submember_parameter_indices": [
                [
                    0,
                    1,
                    2,
                    3
                ]
            ],
            "parameter_labels": null,
            "parameter_bounds": null,
            "identity_vector": [
                1.4142135623730951,
                0.0,
                0.0,
                0.0
            ]
        },
        "4": {
            "module": "pygsti.modelmembers.povms.tppovm",
            "class": "TPPOVM",
            "submembers": [
                2,
                3
            ],
            "state_space": {
                "module": "pygsti.baseobjs.statespace",
                "class": "QubitSpace",
                "version": 0,
                "qudit_labels": [
                    0
                ],
                "qudit_udims": [
                    2
                ],
                "qubit_labels": [
                    0
                ]
            },
            "evotype": "densitymx",
            "model_parameter_indices": [
                3,
                4,
                5,
                6
            ],
            "relative_submember_parameter_indices": [
                [
                    0,
                    1,
                    2,
                    3
                ],
                [
                    0,
                    1,
                    2,
                    3
                ]
            ],
            "parameter_labels": [
                "VecElement Re(0)",
                "VecElement Re(1)",
                "VecElement Re(2)",
                "VecElement Re(3)"
            ],
            "parameter_bounds": null,
            "effect_labels": [
                "0",
                "1"
            ],
            "memberdict_types": [
                "povms"
            ],
            "memberdict_labels": [
                "Mdefault"
            ]
        },
        "5": {
            "module": "pygsti.modelmembers.operations.fulltpop",
            "class": "FullTPOp",
            "submembers": [],
            "state_space": {
                "module": "pygsti.baseobjs.statespace",
                "class": "QubitSpace",
                "version": 0,
                "qudit_labels": [
                    0
                ],
                "qudit_udims": [
                    2
                ],
                "qubit_labels": [
                    0
                ]
            },
            "evotype": "densitymx",
            "model_parameter_indices": [
                7,
                8,
                9,
                10,
                11,
                12,
                13,
                14,
                15,
                16,
                17,
                18
            ],
            "relative_submember_parameter_indices": [],
            "parameter_labels": [
                "MxElement 1,0",
                "MxElement 1,1",
                "MxElement 1,2",
                "MxElement 1,3",
                "MxElement 2,0",
                "MxElement 2,1",
                "MxElement 2,2",
                "MxElement 2,3",
                "MxElement 3,0",
                "MxElement 3,1",
                "MxElement 3,2",
                "MxElement 3,3"
            ],
            "parameter_bounds": null,
            "dense_matrix": [
                [
                    1.0,
                    0.0,
                    0.0,
                    1.0146536357569526e-17
                ],
                [
                    -0.0011493577776841852,
                    0.9009646122522781,
                    0.0037051399805085794,
                    -0.003828107572596339
                ],
                [
                    -0.0006557548791378666,
                    0.008586154977015672,
                    0.893095113257231,
                    -0.004021939816399609
                ],
                [
                    -0.001280631327092053,
                    0.0025907231964787413,
                    -0.004499998585454165,
                    0.901059089879151
                ]
            ],
            "basis": {
                "module": "pygsti.baseobjs.basis",
                "class": "BuiltinBasis",
                "version": 0,
                "name": "pp",
                "sparse": false,
                "state_space": {
                    "module": "pygsti.baseobjs.statespace",
                    "class": "QubitSpace",
                    "version": 0,
                    "qudit_labels": [
                        0
                    ],
                    "qudit_udims": [
                        2
                    ],
                    "qubit_labels": [
                        0
                    ]
                }
            },
            "memberdict_types": [
                "operations"
            ],
            "memberdict_labels": [
                "[]"
            ]
        },
        "6": {
            "module": "pygsti.modelmembers.operations.fulltpop",
            "class": "FullTPOp",
            "submembers": [],
            "state_space": {
                "module": "pygsti.baseobjs.statespace",
                "class": "QubitSpace",
                "version": 0,
                "qudit_labels": [
                    0
                ],
                "qudit_udims": [
                    2
                ],
                "qubit_labels": [
                    0
                ]
            },
            "evotype": "densitymx",
            "model_parameter_indices": [
                19,
                20,
                21,
                22,
                23,
                24,
                25,
                26,
                27,
                28,
                29,
                30
            ],
            "relative_submember_parameter_indices": [],
            "parameter_labels": [
                "MxElement 1,0",
                "MxElement 1,1",
                "MxElement 1,2",
                "MxElement 1,3",
                "MxElement 2,0",
                "MxElement 2,1",
                "MxElement 2,2",
                "MxElement 2,3",
                "MxElement 3,0",
                "MxElement 3,1",
                "MxElement 3,2",
                "MxElement 3,3"
            ],
            "parameter_bounds": null,
            "dense_matrix": [
                [
                    1.0000000000000004,
                    0.0,
                    -1.143450299824811e-16,
                    -1.4353998199084254e-16
                ],
                [
                    -0.0015054347646094755,
                    0.9019844826613417,
                    -0.004745349702858681,
                    -0.003781454274390111
                ],
                [
                    0.0010823818287455315,
                    0.0016026456107831072,
                    0.0033879573125499976,
                    -0.902153608251209
                ],
                [
                    8.1520649440946e-05,
                    -0.002172468767583408,
                    0.9012891103803526,
                    0.0010794299990892124
                ]
            ],
            "basis": {
                "module": "pygsti.baseobjs.basis",
                "class": "BuiltinBasis",
                "version": 0,
                "name": "pp",
                "sparse": false,
                "state_space": {
                    "module": "pygsti.baseobjs.statespace",
                    "class": "QubitSpace",
                    "version": 0,
                    "qudit_labels": [
                        0
                    ],
                    "qudit_udims": [
                        2
                    ],
                    "qubit_labels": [
                        0
                    ]
                }
            },
            "memberdict_types": [
                "operations"
            ],
            "memberdict_labels": [
                "Gxpi2:0"
            ]
        },
        "7": {
            "module": "pygsti.modelmembers.operations.fulltpop",
            "class": "FullTPOp",
            "submembers": [],
            "state_space": {
                "module": "pygsti.baseobjs.statespace",
                "class": "QubitSpace",
                "version": 0,
                "qudit_labels": [
                    0
                ],
                "qudit_udims": [
                    2
                ],
                "qubit_labels": [
                    0
                ]
            },
            "evotype": "densitymx",
            "model_parameter_indices": [
                31,
                32,
                33,
                34,
                35,
                36,
                37,
                38,
                39,
                40,
                41,
                42
            ],
            "relative_submember_parameter_indices": [],
            "parameter_labels": [
                "MxElement 1,0",
                "MxElement 1,1",
                "MxElement 1,2",
                "MxElement 1,3",
                "MxElement 2,0",
                "MxElement 2,1",
                "MxElement 2,2",
                "MxElement 2,3",
                "MxElement 3,0",
                "MxElement 3,1",
                "MxElement 3,2",
                "MxElement 3,3"
            ],
            "parameter_bounds": null,
            "dense_matrix": [
                [
                    1.0000000000000004,
                    1.143450299824811e-16,
                    0.0,
                    -1.4353998199084254e-16
                ],
                [
                    0.0006374847132705318,
                    -0.0002553915701575245,
                    -0.00631811646478213,
                    0.8971494068710624
                ],
                [
                    0.0010886552499225028,
                    0.005436277493411807,
                    0.8941639368767547,
                    -0.0004463079921227456
                ],
                [
                    -0.00030420579755265716,
                    -0.8965043649190871,
                    -0.0019286223164801846,
                    0.0009923131246718068
                ]
            ],
            "basis": {
                "module": "pygsti.baseobjs.basis",
                "class": "BuiltinBasis",
                "version": 0,
                "name": "pp",
                "sparse": false,
                "state_space": {
                    "module": "pygsti.baseobjs.statespace",
                    "class": "QubitSpace",
                    "version": 0,
                    "qudit_labels": [
                        0
                    ],
                    "qudit_udims": [
                        2
                    ],
                    "qubit_labels": [
                        0
                    ]
                }
            },
            "memberdict_types": [
                "operations"
            ],
            "memberdict_labels": [
                "Gypi2:0"
            ]
        }
    }
}